{"routes": [{"overview_polyline": {"points": "ypjgIfmlHjDd@?Np@L^JA}@@M"}, "warnings": ["Walking directions are in beta.    Use caution \u2013 This route may be missing sidewalks or pedestrian paths."], "bounds": {"northeast": {"lat": 53.79868860000001, "lng": -1.5433984}, "southwest": {"lat": 53.7974227, "lng": -1.5437956}}, "waypoint_order": [], "summary": "Lands Ln", "copyrights": "Map data \u00a92019 Google", "legs": [{"distance": {"text": "0.2 km", "value": 171}, "traffic_speed_entry": [], "end_address": "7 Commercial St, Leeds LS1 6AL, UK", "via_waypoint": [], "start_address": "34 Lands Ln, Leeds LS1 6LB, UK", "start_location": {"lat": 53.79868860000001, "lng": -1.5433984}, "steps": [{"html_instructions": "Head <b>south</b> on <b>Lands Ln</b> toward <b>Albion Pl</b>", "distance": {"text": "0.1 km", "value": 96}, "travel_mode": "WALKING", "start_location": {"lat": 53.79868860000001, "lng": -1.5433984}, "polyline": {"points": "ypjgIfmlHjC^^D"}, "duration": {"text": "1 min", "value": 60}, "end_location": {"lat": 53.7978307, "lng": -1.5435851}}, {"html_instructions": "Turn <b>right</b> onto <b>Albion Pl</b>", "distance": {"text": "5 m", "value": 5}, "travel_mode": "WALKING", "maneuver": "turn-right", "start_location": {"lat": 53.7978307, "lng": -1.5435851}, "polyline": {"points": "mkjgIlnlH?N"}, "duration": {"text": "1 min", "value": 4}, "end_location": {"lat": 53.7978292, "lng": -1.5436676}}, {"html_instructions": "Turn <b>left</b> toward <b>Commercial St</b>", "distance": {"text": "46 m", "value": 46}, "travel_mode": "WALKING", "maneuver": "turn-left", "start_location": {"lat": 53.7978292, "lng": -1.5436676}, "polyline": {"points": "mkjgI|nlHp@L^J"}, "duration": {"text": "1 min", "value": 32}, "end_location": {"lat": 53.7974227, "lng": -1.5437956}}, {"html_instructions": "Turn <b>left</b> onto <b>Commercial St</b><div style=\"font-size:0.9em\">Destination will be on the right</div>", "distance": {"text": "24 m", "value": 24}, "travel_mode": "WALKING", "maneuver": "turn-left", "start_location": {"lat": 53.7974227, "lng": -1.5437956}, "polyline": {"points": "{hjgIvolHA}@@M"}, "duration": {"text": "1 min", "value": 17}, "end_location": {"lat": 53.7974247, "lng": -1.5434249}}], "duration": {"text": "2 mins", "value": 113}, "end_location": {"lat": 53.7974247, "lng": -1.5434249}}]}], "status": "OK", "geocoded_waypoints": [{"place_id": "ChIJo_G-uh1ceUgRCkDC06MVxiE", "geocoder_status": "OK", "types": ["beauty_salon", "establishment", "point_of_interest"]}, {"place_id": "ChIJUaVEWBlceUgRjhszk3X93g4", "geocoder_status": "OK", "types": ["establishment", "point_of_interest", "shoe_store", "store"]}]}