{"routes": [{"overview_polyline": {"points": "}gfyHdua@NOIWIUYg@a@e@IGYGWC"}, "warnings": ["Walking directions are in beta.    Use caution \u2013 This route may be missing sidewalks or pedestrian paths."], "bounds": {"northeast": {"lat": 51.4836502, "lng": -0.1768315}, "southwest": {"lat": 51.4829509, "lng": -0.1776303}}, "waypoint_order": [], "summary": "King's Rd/A3217", "copyrights": "Map data \u00a92019 Google", "legs": [{"distance": {"text": "93 m", "value": 93}, "traffic_speed_entry": [], "end_address": "359 King's Rd, Chelsea, London SW3 5ES, UK", "via_waypoint": [], "start_address": "438 King's Rd, Chelsea, London SW10 0LJ, UK", "start_location": {"lat": 51.4830255, "lng": -0.1776303}, "steps": [{"html_instructions": "Head <b>northeast</b> on <b>King's Rd</b>/<b>A3217</b> toward <b>Milman's St</b><div style=\"font-size:0.9em\">Destination will be on the right</div>", "distance": {"text": "93 m", "value": 93}, "travel_mode": "WALKING", "start_location": {"lat": 51.4830255, "lng": -0.1776303}, "polyline": {"points": "}gfyHdua@NOIWCIEKKWIIAAACGIMOCEGECCECMEKAOCG?"}, "duration": {"text": "1 min", "value": 85}, "end_location": {"lat": 51.4836502, "lng": -0.1768315}}], "duration": {"text": "1 min", "value": 85}, "end_location": {"lat": 51.4836502, "lng": -0.1768315}}]}], "status": "OK", "geocoded_waypoints": [{"place_id": "ChIJQyety3oFdkgRPKhoxC6z-A4", "geocoder_status": "OK", "types": ["premise"]}, {"place_id": "ChIJDzM8UmUFdkgRkKMVDjGZhSk", "geocoder_status": "OK", "types": ["premise"]}]}