{"routes": [{"overview_polyline": {"points": "sw}sI`u}XlFtA|Cz@OjCOdClA\\"}, "warnings": ["Walking directions are in beta.    Use caution \u2013 This route may be missing sidewalks or pedestrian paths."], "bounds": {"northeast": {"lat": 55.8631357, "lng": -4.2531275}, "southwest": {"lat": 55.8609252, "lng": -4.2553777}}, "waypoint_order": [], "summary": "Buchanan St", "copyrights": "Map data \u00a92019 Google", "legs": [{"distance": {"text": "0.4 km", "value": 355}, "traffic_speed_entry": [], "end_address": "16 W Nile St, Glasgow G1 2PW, UK", "via_waypoint": [], "start_address": "Buchanan galleries, 220 Buchanan St, Glasgow G1 2FF, UK", "start_location": {"lat": 55.8631357, "lng": -4.2531275}, "steps": [{"html_instructions": "Head <b>south</b> on <b>Buchanan St</b> toward <b>Dundas Ln</b>", "distance": {"text": "0.2 km", "value": 224}, "travel_mode": "WALKING", "start_location": {"lat": 55.8631357, "lng": -4.2531275}, "polyline": {"points": "sw}sI`u}XlAXfAZdAVPFB?xCz@"}, "duration": {"text": "2 mins", "value": 143}, "end_location": {"lat": 55.86115950000001, "lng": -4.2538615}}, {"html_instructions": "Turn <b>right</b> onto <b>St Vincent St</b>", "distance": {"text": "87 m", "value": 87}, "travel_mode": "WALKING", "maneuver": "turn-right", "start_location": {"lat": 55.86115950000001, "lng": -4.2538615}, "polyline": {"points": "gk}sIry}XInAEz@APMrB"}, "duration": {"text": "1 min", "value": 70}, "end_location": {"lat": 55.86131529999999, "lng": -4.2552347}}, {"html_instructions": "Turn <b>left</b> onto <b>W Nile St</b><div style=\"font-size:0.9em\">Destination will be on the right</div>", "distance": {"text": "44 m", "value": 44}, "travel_mode": "WALKING", "maneuver": "turn-left", "start_location": {"lat": 55.86131529999999, "lng": -4.2552347}, "polyline": {"points": "gl}sIdb~XXHr@R"}, "duration": {"text": "1 min", "value": 29}, "end_location": {"lat": 55.8609252, "lng": -4.2553777}}], "duration": {"text": "4 mins", "value": 242}, "end_location": {"lat": 55.8609252, "lng": -4.2553777}}]}], "status": "OK", "geocoded_waypoints": [{"place_id": "ChIJ2TNU9B9EiEgRZfeW2_wZUjc", "geocoder_status": "OK", "types": ["premise"]}, {"place_id": "ChIJv8KitZ9GiEgRS-JtEk-bNxw", "geocoder_status": "OK", "types": ["street_address"]}]}