{"routes": [{"overview_polyline": {"points": "uyleIxruLNqAcAe@_EaC"}, "warnings": ["Walking directions are in beta.    Use caution \u2013 This route may be missing sidewalks or pedestrian paths."], "bounds": {"northeast": {"lat": 53.4838858, "lng": -2.2444759}, "southwest": {"lat": 53.4825899, "lng": -2.245726}}, "waypoint_order": [], "summary": "Exchange St and New Cathedral St", "copyrights": "Map data \u00a92019 Google", "legs": [{"distance": {"text": "0.2 km", "value": 183}, "traffic_speed_entry": [], "end_address": "22 New Cathedral Street, Manchester M1 1AD, UK", "via_waypoint": [], "start_address": "2-4 St Anns Square, Manchester M2 7HD, UK", "start_location": {"lat": 53.4826661, "lng": -2.245726}, "steps": [{"html_instructions": "Head <b>east</b> on <b>Barton Square</b> toward <b>St Anns Square</b>", "distance": {"text": "28 m", "value": 28}, "travel_mode": "WALKING", "start_location": {"lat": 53.4826661, "lng": -2.245726}, "polyline": {"points": "uyleIxruLFe@Fk@"}, "duration": {"text": "1 min", "value": 24}, "end_location": {"lat": 53.4825899, "lng": -2.2453181}}, {"html_instructions": "Turn <b>left</b> onto <b>Exchange St</b>", "distance": {"text": "80 m", "value": 80}, "travel_mode": "WALKING", "maneuver": "turn-left", "start_location": {"lat": 53.4825899, "lng": -2.2453181}, "polyline": {"points": "eyleIfpuLy@_@IEcAi@"}, "duration": {"text": "1 min", "value": 54}, "end_location": {"lat": 53.4832652, "lng": -2.2449159}}, {"html_instructions": "Continue onto <b>New Cathedral St</b>", "distance": {"text": "75 m", "value": 75}, "travel_mode": "WALKING", "start_location": {"lat": 53.4832652, "lng": -2.2449159}, "polyline": {"points": "m}leIvmuL{BwA"}, "duration": {"text": "1 min", "value": 50}, "end_location": {"lat": 53.4838858, "lng": -2.2444759}}], "duration": {"text": "2 mins", "value": 128}, "end_location": {"lat": 53.4838858, "lng": -2.2444759}}]}], "status": "OK", "geocoded_waypoints": [{"place_id": "ChIJO44W-sOxe0gRd4yKS-JVliM", "geocoder_status": "OK", "types": ["premise"]}, {"place_id": "ChIJf9Tdusaxe0gRRfkMwV604ds", "geocoder_status": "OK", "types": ["street_address"]}]}