{"routes": [{"overview_polyline": {"points": "iysfIpmcHGG_ALKiGIoG@g@FCzBiCJO"}, "warnings": ["Walking directions are in beta.    Use caution \u2013 This route may be missing sidewalks or pedestrian paths."], "bounds": {"northeast": {"lat": 53.68275879999999, "lng": -1.4937225}, "southwest": {"lat": 53.68202549999999, "lng": -1.4973971}}, "waypoint_order": [], "summary": "Kirkgate", "copyrights": "Map data \u00a92019 Google", "legs": [{"distance": {"text": "0.3 km", "value": 329}, "traffic_speed_entry": [], "end_address": "86 Kirkgate, Wakefield WF1 1TB, UK", "via_waypoint": [], "start_address": "The Ridings Centre, 89 Cathedral Walk, Wakefield WF1 1YD, UK", "start_location": {"lat": 53.6822878, "lng": -1.4973737}, "steps": [{"html_instructions": "Head <b>north</b> on <b>Cathedral Walk</b>/<b>Southgate</b> toward <b>Kirkgate</b><div style=\"font-size:0.9em\">Continue to follow Southgate</div>", "distance": {"text": "42 m", "value": 42}, "travel_mode": "WALKING", "start_location": {"lat": 53.6822878, "lng": -1.4973737}, "polyline": {"points": "iysfIpmcHGG_AL"}, "duration": {"text": "1 min", "value": 31}, "end_location": {"lat": 53.6826523, "lng": -1.4973971}}, {"html_instructions": "Turn <b>right</b> onto <b>Kirkgate</b>", "distance": {"text": "0.2 km", "value": 191}, "travel_mode": "WALKING", "maneuver": "turn-right", "start_location": {"lat": 53.6826523, "lng": -1.4973971}, "polyline": {"points": "q{sfIvmcHCg@GaF?e@IiF@g@"}, "duration": {"text": "2 mins", "value": 121}, "end_location": {"lat": 53.6827501, "lng": -1.4945121}}, {"html_instructions": "Turn <b>right</b> to stay on <b>Kirkgate</b><div style=\"font-size:0.9em\">Destination will be on the right</div>", "distance": {"text": "0.1 km", "value": 96}, "travel_mode": "WALKING", "maneuver": "turn-right", "start_location": {"lat": 53.6827501, "lng": -1.4945121}, "polyline": {"points": "e|sfIt{bHFCFCrBeCJO"}, "duration": {"text": "1 min", "value": 66}, "end_location": {"lat": 53.68202549999999, "lng": -1.4937225}}], "duration": {"text": "4 mins", "value": 218}, "end_location": {"lat": 53.68202549999999, "lng": -1.4937225}}]}], "status": "OK", "geocoded_waypoints": [{"place_id": "ChIJPVhxaP5meUgR35g1tOj05Ik", "geocoder_status": "OK", "types": ["street_address"]}, {"place_id": "ChIJE6_X5NFneUgRsKgv--7aan4", "geocoder_status": "OK", "types": ["atm", "establishment", "finance", "point_of_interest"]}]}