{"routes": [{"overview_polyline": {"points": "mgjyHdbNfAdATRG\\Gh@CRBTDJQl@a@|AQl@NLBG"}, "warnings": ["Walking directions are in beta.    Use caution \u2013 This route may be missing sidewalks or pedestrian paths."], "bounds": {"northeast": {"lat": 51.50342939999999, "lng": -0.07730759999999999}, "southwest": {"lat": 51.5029617, "lng": -0.07939489999999999}}, "waypoint_order": [], "summary": "Duchess Walk and A200", "copyrights": "Map data \u00a92019 Google", "legs": [{"distance": {"text": "0.2 km", "value": 194}, "traffic_speed_entry": [], "end_address": "Tower Mini Market, 188 Tooley St, London SE1 2TZ, UK", "via_waypoint": [], "start_address": "6 Duchess Walk, London SE1 2SD, UK", "start_location": {"lat": 51.50342939999999, "lng": -0.07730759999999999}, "steps": [{"html_instructions": "Head <b>southwest</b> on <b>Duchess Walk</b> toward <b>Still Walk</b>", "distance": {"text": "65 m", "value": 65}, "travel_mode": "WALKING", "start_location": {"lat": 51.50342939999999, "lng": -0.07730759999999999}, "polyline": {"points": "mgjyHdbNVTn@n@TR"}, "duration": {"text": "1 min", "value": 49}, "end_location": {"lat": 51.5029617, "lng": -0.0777556}}, {"html_instructions": "Turn <b>right</b> onto <b>Queen Elizabeth St</b>/<b>A200</b>", "distance": {"text": "47 m", "value": 47}, "travel_mode": "WALKING", "maneuver": "turn-right", "start_location": {"lat": 51.5029617, "lng": -0.0777556}, "polyline": {"points": "odjyH~dNG\\CTCRAFAJ?F?D@B@B@DBD"}, "duration": {"text": "1 min", "value": 35}, "end_location": {"lat": 51.5030095, "lng": -0.0783932}}, {"html_instructions": "Turn <b>right</b> onto <b>Tooley St</b>/<b>A200</b>", "distance": {"text": "78 m", "value": 78}, "travel_mode": "WALKING", "maneuver": "turn-right", "start_location": {"lat": 51.5030095, "lng": -0.0783932}, "polyline": {"points": "ydjyH|hNGVITI\\K\\ELERQl@NL"}, "duration": {"text": "1 min", "value": 55}, "end_location": {"lat": 51.5032784, "lng": -0.07939489999999999}}, {"html_instructions": "Cross the road<div style=\"font-size:0.9em\">Destination will be on the right</div>", "distance": {"text": "4 m", "value": 4}, "travel_mode": "WALKING", "start_location": {"lat": 51.5032784, "lng": -0.07939489999999999}, "polyline": {"points": "ofjyHdoNBG"}, "duration": {"text": "1 min", "value": 13}, "end_location": {"lat": 51.5032626, "lng": -0.0793511}}], "duration": {"text": "3 mins", "value": 152}, "end_location": {"lat": 51.5032626, "lng": -0.0793511}}]}], "status": "OK", "geocoded_waypoints": [{"place_id": "ChIJEcLP7kUDdkgRnYw6Ilj_418", "geocoder_status": "OK", "types": ["street_address"]}, {"place_id": "ChIJiww3C0UDdkgRB_O77TDL1Xs", "geocoder_status": "OK", "types": ["premise"]}]}