{"routes": [{"overview_polyline": {"points": "gkjgInhlHElEG~GyAIaDA]C"}, "warnings": ["Walking directions are in beta.    Use caution \u2013 This route may be missing sidewalks or pedestrian paths."], "bounds": {"northeast": {"lat": 53.7992839, "lng": -1.5426443}, "southwest": {"lat": 53.7978004, "lng": -1.5451061}}, "waypoint_order": [], "summary": "Albion Pl", "copyrights": "Map data \u00a92019 Google", "legs": [{"distance": {"text": "0.3 km", "value": 319}, "traffic_speed_entry": [], "end_address": "105 Albion St, Leeds LS1 5AS, UK", "via_waypoint": [], "start_address": "19 Albion Pl, Leeds LS1 6JS, UK", "start_location": {"lat": 53.7978004, "lng": -1.5426443}, "steps": [{"html_instructions": "Head <b>west</b> on <b>Albion Pl</b> toward <b>Lands Ln</b>", "distance": {"text": "0.2 km", "value": 162}, "travel_mode": "WALKING", "start_location": {"lat": 53.7978004, "lng": -1.5426443}, "polyline": {"points": "gkjgInhlHE|D?NG~G"}, "duration": {"text": "2 mins", "value": 127}, "end_location": {"lat": 53.7978712, "lng": -1.5451061}}, {"html_instructions": "Turn <b>right</b> onto <b>Albion St</b><div style=\"font-size:0.9em\">Destination will be on the right</div>", "distance": {"text": "0.2 km", "value": 157}, "travel_mode": "WALKING", "maneuver": "turn-right", "start_location": {"lat": 53.7978712, "lng": -1.5451061}, "polyline": {"points": "ukjgI|wlHyAIG?yCA]C"}, "duration": {"text": "2 mins", "value": 132}, "end_location": {"lat": 53.7992839, "lng": -1.545032}}], "duration": {"text": "4 mins", "value": 259}, "end_location": {"lat": 53.7992839, "lng": -1.545032}}]}], "status": "OK", "geocoded_waypoints": [{"place_id": "ChIJBW-23xtceUgR6uceNcqjLJ8", "geocoder_status": "OK", "types": ["street_address"]}, {"place_id": "ChIJV0LUdRxceUgRsCRgyTTQ2AE", "geocoder_status": "OK", "types": ["street_address"]}]}